RetinaFacePostProcessing/__init__.py
RetinaFacePostProcessing/retinaface_post_processing.py
retinaface_post_processing-0.0.4.dist-info/LICENSE
retinaface_post_processing-0.0.4.dist-info/METADATA
retinaface_post_processing-0.0.4.dist-info/WHEEL
retinaface_post_processing-0.0.4.dist-info/top_level.txt
retinaface_post_processing-0.0.4.dist-info/RECORD
