Metadata-Version: 2.1
Name: retinaface-post-processing
Version: 0.0.4
Summary: RetinaFace Post-Processing is a module contains code for post-processing of RetinaFace inference results
Home-page: https://github.com/dl-wb-experiments/retinaface-post-processing
Author: Tugaryov Artyom
Author-email: artyom.tugarev@intel.com
License: OSI Approved :: Apache Software License
Platform: UNKNOWN
Classifier: Programming Language :: Python :: 3
Classifier: License :: OSI Approved :: Apache Software License
Classifier: Operating System :: OS Independent
Requires-Python: >=3.6
License-File: LICENSE
Requires-Dist: numpy (==1.19.5)
